{"id":"e8ef2e6c-f0af-4f0c-960a-b4b21aef6bd2","timestamp":1731042086957,"matcher":{"static":{},"wildcard":{},"dynamic":{}},"prerendered":["/Solido/awesome-flutter","/jtoy/awesome-tensorflow","/XamSome/awesome-xamarin","/alebcay/awesome-shell","/ziadoz/awesome-php","/agarrharr/awesome-cli-apps","/akullpp/awesome-java","/sorrycc/awesome-javascript","/vinta/awesome-python","/sindresorhus/awesome-nodejs","/fffaraz/awesome-cpp","/quozd/awesome-dotnet","/markets/awesome-ruby","/awesome-selfhosted/awesome-selfhosted","/aniftyco/awesome-tailwindcss","/matteocrippa/awesome-swift","/rockerBOO/awesome-neovim","/rust-unofficial/awesome-rust","/KotlinBy/awesome-kotlin","/chiraggude/awesome-laravel","/vsouza/awesome-ios","/lauris/awesome-scala","/vuejs/awesome-vue","/avelino/awesome-go","/","/h4cc/awesome-elixir"]}